Workbook

Sheet Model
A1: All the values in the model are in Crores(cr.) | B1: 2016 | C1: =B1+1 -> 2017 | D1: =C1+1 -> 2018 | E1: =D1+1 -> 2019 | F1: =E1+1 -> 2020 | G1: =F1+1 -> 2021 | H1: =G1+1 -> 2022 | I1: =H1+1 -> 2023 | J1: =I1+1 -> 2024 | ... V1: =U1+1 -> 2036 | W1: TV
A2: Revenue
A3: Gross Revenue from operations | B3: 30700.88 | C3: 30871.59 | D3: 32871.82 | E3: 33650.54 | F3: 28836.09 | G3: 30800.62 | H3: 29245.47 | I3: 33805.65 | J3: 37455.72 | K3: =(K99*K120)/(10^7) -> 50446.579 | L3: =(L99*L120)/(10^7) -> 61484.01 | M3: =(M99*M120)/(10^7) -> 74983.272 | N3: =(N99*N120)/(10^7) -> 91500.751 | O3: =(O99*O120)/(10^7) -> 111719.69 | P3: =(P99*P120)/(10^7) -> 136479.28
A4: Other Income | B4: 422 | C4: 522.43 | D4: 525.82 | E4: 691.25 | F4: 778.34 | G4: 579.85 | H4: 556.91 | I4: 565.16 | J4: 892.55 | K4: =MEDIAN(B4:J4) -> 565.16 | L4: =K4 -> 565.16 | M4: =L4 -> 565.16 | N4: =M4 -> 565.16 | O4: =N4 -> 565.16 | P4: =O4 -> 565.16
A6: Total Revenue | B6: =SUM(B3:B4) -> 31122.88 | C6: =SUM(C3:C4) -> 31394.02 | D6: =SUM(D3:D4) -> 33397.64 | E6: =SUM(E3:E4) -> 34341.79 | F6: =SUM(F3:F4) -> 29614.43 | G6: =SUM(G3:G4) -> 31380.47 | H6: =SUM(H3:H4) -> 29802.38 | I6: =SUM(I3:I4) -> 34370.81 | ... P6: =SUM(P3:P4) -> 137044.44
A8: Costs
A9: Raw Materials | B9: 19321.72 | C9: 18974.11 | D9: 21857.79 | E9: 23346.1 | F9: 19867.19 | G9: 21875.33 | H9: 20708.07 | I9: 24019.73 | J9: 24767.46 | K9: =K$3*K125 -> 34555.907 | L9: =L$3*L125 -> 42116.547 | M9: =M$3*M125 -> 51363.542 | N9: =N$3*N125 -> 62678.015 | O9: =O$3*O125 -> 76527.987 | P9: =P$3*P125 -> 93488.303
A10: Purchases | G10: 30.46 | H10: 45.95 | I10: 47.43 | J10: 484.2 | K10: =K$3*K126 -> 652.13627 | L10: =L$3*L126 -> 794.82006 | M10: =M$3*M126 -> 969.3286 | N10: =N$3*N126 -> 1182.8544 | O10: =O$3*O126 -> 1444.23 | P10: =P$3*P126 -> 1764.3037
A11: Changes in Stock in Trade | B11: -11.88 | C11: 63.17 | D11: -23.15 | E11: -28.38 | F11: -169.78 | G11: -143.46 | H11: 72.71 | I11: -209.04 | J11: 179.11 | K11: =K$3*K127 -> 241.23116 | L11: =L$3*L127 -> 294.0112 | M11: =M$3*M127 -> 358.5635 | N11: =N$3*N127 -> 437.54865 | O11: =O$3*O127 -> 534.23385 | P11: =P$3*P127 -> 652.63204
A12: Employee Cost | B12: 1315.93 | C12: 1396.01 | D12: 1540.13 | E12: 1730.24 | F12: 1841.7 | G12: 1898.72 | H12: 1935.44 | I12: 2189.83 | J12: 2402.34 | K12: =K$3*K128 -> 3279.0276 | L12: =L$3*L128 -> 3996.4607 | M12: =M$3*M128 -> 4873.9127 | N12: =N$3*N128 -> 5947.5488 | O12: =O$3*O128 -> 7261.7798 | P12: =P$3*P128 -> 8871.1529
A13: Other Expenses | B13: 3361.96 | C13: 3432.36 | D13: 3575.53 | E13: 3672.49 | F13: 3339.02 | G13: 3120.33 | H13: 3114.53 | I13: 3771.47 | J13: 4366.9 | K13: =K$3*K129 -> 5549.1237 | L13: =L$3*L129 -> 6763.2411 | M13: =M$3*M129 -> 8248.16 | N13: =N$3*N129 -> 10065.083 | O13: =O$3*O129 -> 12289.166 | P13: =P$3*P129 -> 15012.72
A14: Excise Duty | B14: 2258.18 | C14: 2371.13 | D14: 641.33 | E14: 0 | F14: 0 | G14: 0 | H14: 0 | I14: 0 | J14: 0 | K14: 0 | L14: 0 | M14: 0 | N14: 0 | O14: 0 | P14: 0
A16: Total Costs | B16: =SUM(B9:B14) -> 26245.91 | C16: =SUM(C9:C14) -> 26236.78 | D16: =SUM(D9:D14) -> 27591.63 | E16: =SUM(E9:E14) -> 28720.45 | F16: =SUM(F9:F14) -> 24878.13 | G16: =SUM(G9:G14) -> 26781.38 | H16: =SUM(H9:H14) -> 25876.7 | I16: =SUM(I9:I14) -> 29819.42 | ... P16: =SUM(P9:P14) -> 119789.11
A18: Operating Profits | B18: =B6-B16 -> 4876.97 | C18: =C6-C16 -> 5157.24 | D18: =D6-D16 -> 5806.01 | E18: =E6-E16 -> 5621.34 | F18: =F6-F16 -> 4736.3 | G18: =G6-G16 -> 4599.09 | H18: =H6-H16 -> 3925.68 | I18: =I6-I16 -> 4551.39 | ... P18: =P6-P16 -> 17255.323
A20: Depreciation & Amortization | B20: 437.64 | C20: 492.73 | D20: 555.6 | E20: 602.01 | F20: 817.96 | G20: 676.87 | H20: 649.75 | I20: 656.96 | J20: 711.41 | K20: =K204 -> 793.1 | L20: =L204 -> 854.7 | M20: =M204 -> 916.3 | N20: =N204 -> 977.9 | O20: =O204 -> 1039.5 | P20: =P204 -> 1101.1
A22: EBIT | B22: =B18-B20 -> 4439.33 | C22: =C18-C20 -> 4664.51 | D22: =D18-D20 -> 5250.41 | E22: =E18-E20 -> 5019.33 | F22: =F18-F20 -> 3918.34 | G22: =G18-G20 -> 3922.22 | H22: =H18-H20 -> 3275.93 | I22: =I18-I20 -> 3894.43 | ... P22: =P18-P20 -> 16154.223
A24: Interest | B24: 4.89 | C24: 6.05 | D24: 6.25 | E24: 8.6 | F24: 22.02 | G24: 21.84 | I24: 19.87 | J24: 18.5 | K24: =J24 -> 18.5 | L24: =K24 -> 18.5 | M24: =L24 -> 18.5 | N24: =M24 -> 18.5 | O24: =N24 -> 18.5 | P24: =O24 -> 18.5
A26: Profit Before Exceptional Items and Taxes | B26: =B22-B24 -> 4434.44 | C26: =C22-C24 -> 4658.46 | D26: =D22-D24 -> 5244.16 | E26: =E22-E24 -> 5010.73 | F26: =F22-F24 -> 3896.32 | G26: =G22-G24 -> 3900.38 | H26: =H22-H24 -> 3275.93 | I26: =I22-I24 -> 3874.56 | ... P26: =P22-P24 -> 16135.723
A27: Other/Exceptional Items(income) | F27: 737.48
A28: Other/Exceptional Items | B28: 0 | F28: -60.1 | J28: -160
A29: Profit Before Taxes | B29: =SUM(B26:B28) -> 4434.44 | C29: =SUM(C26:C28) -> 4658.46 | D29: =SUM(D26:D28) -> 5244.16 | E29: =SUM(E26:E28) -> 5010.73 | F29: =SUM(F26:F28) -> 4573.7 | G29: =SUM(G26:G28) -> 3900.38 | H29: =SUM(H26:H28) -> 3275.93 | I29: =SUM(I26:I28) -> 3874.56 | ... P29: =SUM(P26:P28) -> 16135.723
A31: Taxes | B31: 1274.68 | C31: 1281.34 | D31: 1546.8 | E31: 1625.86 | F31: 940.43 | G31: 936.18 | H31: 777.11 | I31: 963.98 | J31: 1290.4 | K31: =K29*K32 -> 1776.8141 | L31: =L29*L32 -> 2163.2671 | M31: =M29*M32 -> 2640.0378 | N31: =N29*N32 -> 3227.5386 | O31: =O29*O32 -> 3950.8358 | P31: =P29*P32 -> 4840.7168
F32: =F31/F29 -> 0.2056169 | G32: =G31/G29 -> 0.24002277 | H32: =H31/H29 -> 0.23721813 | I32: =I31/I29 -> 0.24879728 | J32: =J31/J29 -> 0.24540017 | K32: 0.3 | L32: =K32 -> 0.3 | M32: =L32 -> 0.3 | N32: =M32 -> 0.3 | O32: =N32 -> 0.3 | P32: =O32 -> 0.3
A33: Profit Before Minority Interest and Share in Associates | B33: =B29-B31 -> 3159.76 | C33: =C29-C31 -> 3377.12 | D33: =D29-D31 -> 3697.36 | E33: =E29-E31 -> 3384.87 | F33: =F29-F31 -> 3633.27 | G33: =G29-G31 -> 2964.2 | H33: =H29-H31 -> 2498.82 | I33: =I29-I31 -> 2910.58 | ... P33: =P29-P31 -> 11295.006
A37: Profit for the Year | B37: =B33+B34 -> 3159.76 | C37: =C33+C34 -> 3377.12 | D37: =D33+D34 -> 3697.36 | E37: =E33+F34 -> 3384.87 | F37: =F33+F34 -> 3633.27 | G37: =G33+G34 -> 2964.2 | H37: =H33+H34 -> 2498.82 | I37: =I33+I34 -> 2910.58 | J37: =J33+J34 -> 3967.95 | K37: =K33+K34 -> 4145.8996 | L37: =L33+L34 -> 5047.6231 | M37: =M33+M34 -> 6160.0882 | ... P37: =P33+P34 -> 11295.006
A40: Sources of Funds
A42: Shareholder Funds
A43: Share Capital | B43: 39.94 | C43: 40 | D43: 40 | E43: 40 | F43: 40 | G43: 40 | H43: 40 | I43: 40 | J43: 39.98 | K43: 40 | L43: =K43 -> 40 | M43: =L43 -> 40 | N43: =M43 -> 40 | O43: =N43 -> 40 | P43: =O43 -> 40
A44: Reserves & Surplus | B44: 8794.47 | C44: 10071 | D44: 11729 | E44: 12817 | F44: 14096 | G44: 15158 | H44: 15743 | I44: 16665 | J44: 17946.2 | K44: =J44+K37 -> 22092.1 | L44: =K44+L37 -> 27139.723 | M44: =L44+M37 -> 33299.811 | N44: =M44+N37 -> 40830.734 | O44: =N44+O37 -> 50049.351 | P44: =O44+P37 -> 61344.357
A45: Total Equity | B45: =SUM(B43:B44) -> 8834.41 | C45: =SUM(C43:C44) -> 10111 | D45: =SUM(D43:D44) -> 11769 | E45: =SUM(E43:E44) -> 12857 | F45: =SUM(F43:F44) -> 14136 | G45: =SUM(G43:G44) -> 15198 | H45: =SUM(H43:H44) -> 15783 | I45: =SUM(I43:I44) -> 16705 | ... P45: =SUM(P43:P44) -> 61384.357
A50: Long Term Liabilities | B50: =SUM(B51:B54) -> 290.13 | C50: =SUM(C51:C54) -> 489.64 | D50: =SUM(D51:D54) -> 626.6 | E50: =SUM(E51:E54) -> 653.71 | F50: =SUM(F51:F54) -> 636.87 | G50: =SUM(G51:G54) -> 852.4 | H50: =SUM(H51:H54) -> 858.72 | I50: =SUM(I51:I54) -> 934.07 | ... P50: =SUM(P51:P54) -> 1041.11
A51: Lease/Loans | B51: 0 | C51: 0 | D51: 0 | E51: 0 | F51: 121.67 | G51: 129.81 | H51: 142.32 | I51: 134.29 | J51: 111.5 | K51: =J51 -> 111.5 | L51: =K51 -> 111.5 | M51: =L51 -> 111.5 | N51: =M51 -> 111.5 | O51: =N51 -> 111.5 | P51: =O51 -> 111.5
A52: Other Long Term Liabilities | B52: 0 | C52: 0 | D52: 0 | E52: 0 | F52: 0 | G52: 146.04 | H52: 155.04 | I52: 196.29 | J52: 178.13 | K52: =J52 -> 178.13 | L52: =K52 -> 178.13 | M52: =L52 -> 178.13 | N52: =M52 -> 178.13 | O52: =N52 -> 178.13 | P52: =O52 -> 178.13
A53: Long Term Provisions | B53: 67.6 | C53: 75.3 | D53: 114.94 | E53: 117.2 | F53: 122.37 | G53: 172.46 | H53: 178.07 | I53: 198.12 | J53: 316.66 | K53: =J53 -> 316.66 | L53: =K53 -> 316.66 | M53: =L53 -> 316.66 | N53: =M53 -> 316.66 | O53: =N53 -> 316.66 | P53: =O53 -> 316.66
A54: Deferred Tax Liabilities | B54: 222.53 | C54: 414.34 | D54: 511.66 | E54: 536.51 | F54: 392.83 | G54: 404.09 | H54: 383.29 | I54: 405.37 | J54: 434.82 | K54: =J54 -> 434.82 | L54: =K54 -> 434.82 | M54: =L54 -> 434.82 | N54: =M54 -> 434.82 | O54: =N54 -> 434.82 | P54: =O54 -> 434.82
A56: Current Liabilities | B56: =SUM(B58:B62) -> 3448.32 | C56: =SUM(C58:C62) -> 4093.33 | D56: =SUM(D58:D62) -> 4343.32 | E56: =SUM(E58:E62) -> 4130.36 | F56: =SUM(F58:F62) -> 3976.06 | G56: =SUM(G58:G62) -> 6110.61 | H56: =SUM(H58:H62) -> 5072.38 | I56: =SUM(I58:I62) -> 5623.98 | ... P56: =SUM(P58:P62) -> 24174.342
A58: Short Term Borrowings | C58: 0 | D58: 0 | E58: 0 | F58: 28.29 | G58: 19.7 | H58: 25.75 | I58: 22.02 | J58: 26.08 | K58: =K164 -> 35.12539 | L58: =L164 -> 42.81063 | M58: =M164 -> 52.210016 | N58: =N164 -> 63.710952 | O58: =O164 -> 77.789173 | P58: =P164 -> 95.028997
A59: Trade Payables | B59: 2650.56 | C59: 3247.27 | D59: 3318.81 | E59: 3355.28 | F59: =8.33+3022.18 -> 3030.51 | G59: 5205 | H59: =25.55+4234.79 -> 4260.34 | I59: =4703.31+1.15 -> 4704.46 | J59: =15.79+5512.36 -> 5528.15 | K59: =K165 -> 7566.9869 | L59: =L165 -> 9222.6015 | M59: =M165 -> 11247.491 | N59: =N165 -> 13725.113 | O59: =O165 -> 16757.953 | P59: =P165 -> 20471.891
A60: Other Current Liabilities | B60: 502.4 | C60: 454.28 | D60: 762.58 | E60: 495.18 | F60: 518.26 | G60: 566.01 | H60: 492.12 | I60: 557.84 | J60: 585.6 | K60: =K166 -> 788.70508 | L60: =L166 -> 961.26937 | M60: =M166 -> 1172.3231 | N60: =N166 -> 1430.5649 | O60: =O166 -> 1746.6771 | P60: =P166 -> 2133.7799
A61: Short Term Provisions | B61: 29.66 | C61: 39.01 | D61: 59.79 | E61: 59.03 | F61: 146.56 | G61: 160.37 | H61: 160.42 | I61: 175.69 | J61: 154.14 | K61: =K167 -> 207.60075 | L61: =L167 -> 253.02264 | M61: =M167 -> 308.57561 | N61: =N167 -> 376.54932 | O61: =O167 -> 459.75549 | P61: =P167 -> 561.64761
A62: Other Finance Liabilities | B62: 265.7 | C62: 352.77 | D62: 202.14 | E62: 220.87 | F62: 252.44 | G62: 159.53 | H62: 133.75 | I62: 163.97 | J62: 250.29 | K62: =K168 -> 337.09869 | L62: =L168 -> 410.85401 | M62: =M168 -> 501.06001 | N62: =N168 -> 611.4346 | O62: =O168 -> 746.54341 | P62: =P168 -> 911.99416
A63: Total | B63: =SUM(B45,B50,B56) -> 12572.86 | C63: =SUM(C45,C50,C56) -> 14693.97 | D63: =SUM(D45,D50,D56) -> 16738.92 | E63: =SUM(E45,E50,E56) -> 17641.07 | F63: =SUM(F45,F50,F56) -> 18748.93 | G63: =SUM(G45,G50,G56) -> 22161.01 | H63: =SUM(H45,H50,H56) -> 21714.1 | I63: =SUM(I45,I50,I56) -> 23263.05 | ... P63: =SUM(P45,P50,P56) -> 86599.809
A66: Application Of Funds
A68: Long Term Assets | B68: =SUM(B69:B79) -> 6421.64 | C68: =SUM(C69:C79) -> 7241.08 | D68: =SUM(D69:D79) -> 7890.62 | E68: =SUM(E69:E79) -> 9525.55 | F68: =SUM(F69:F79) -> 10460.77 | G68: =SUM(G69:G79) -> 11208.26 | H68: =SUM(H69:H79) -> 11599.06 | I68: =SUM(I69:I79) -> 14226.35 | ... P68: =SUM(P69:P79) -> 18745.84
A69: Tangible Assets(PPE) | B69: 3465.46 | C69: 4310.73 | D69: 4485.89 | E69: 4477.53 | F69: 5562.42 | G69: 5293.4 | H69: 5094.39 | I69: 4868.2 | J69: 4933.87 | K69: =SUM(J69:J73,K202)-K204 -> 6792.85 | L69: =SUM(K69:K73,L202)-L204 -> 7291.25 | M69: =SUM(L69:L73,M202)-M204 -> 7789.65 | N69: =SUM(M69:M73,N202)-N204 -> 8288.05 | O69: =SUM(N69:N73,O202)-O204 -> 8786.45 | P69: =SUM(O69:O73,P202)-P204 -> 9284.85
A70: Intangible Assets | B70: 118.89 | C70: 84.86 | D70: 168.65 | E70: 141.05 | F70: 140.09 | G70: 290.26 | H70: 298.5 | I70: 500.19 | J70: 528.55
A71: Rights of Use Assets | C71: 0 | D71: 0 | E71: 0 | F71: 414.57 | G71: 404.75 | H71: 413.59 | I71: 393.03 | J71: 371.61
A72: Capital Work in Progress | B72: 288.34 | C72: 270.72 | D72: 203.78 | E72: 360.67 | F72: 160.25 | G72: 177.86 | H72: 87.32 | I72: 128.55 | J72: 120.58
A73: Intangible Assets Under Development | B73: 317.06 | C73: 194.33 | D73: 114.61 | E73: 181.19 | F73: 181.02 | G73: 258.73 | H73: 370.88 | I73: 335.24 | J73: 359.93
A75: Non-Current Investments | B75: 1111.91 | C75: 1349 | D75: 1934.08 | E75: 2801.51 | F75: 3528.17 | G75: 4308.18 | H75: 4814.66 | I75: 7372.48 | J75: 8811.58 | K75: =J75 -> 8811.58 | L75: =K75 -> 8811.58 | M75: =L75 -> 8811.58 | N75: =M75 -> 8811.58 | O75: =N75 -> 8811.58 | P75: =O75 -> 8811.58
A76: Other Financial Assets | B76: 23.2 | C76: 0 | D76: 0 | E76: 0 | F76: 0 | G76: 35.5 | H76: 41.6 | I76: 205.65 | J76: 188.87 | K76: =J76 -> 188.87 | L76: =K76 -> 188.87 | M76: =L76 -> 188.87 | N76: =M76 -> 188.87 | O76: =N76 -> 188.87 | P76: =O76 -> 188.87
A77: Long Term Loans and Advances | B77: 26.7 | C77: 48.36 | D77: 45.68 | E77: 59.96 | F77: 67.27 | G77: 16.73 | H77: 17.43 | I77: 19.87 | J77: 21.15 | K77: =J77 -> 21.15 | L77: =K77 -> 21.15 | M77: =L77 -> 21.15 | N77: =M77 -> 21.15 | O77: =N77 -> 21.15 | P77: =O77 -> 21.15
A78: Other Non Current Assets | B78: 842.54 | C78: 651.14 | D78: 558.67 | E78: 664.38 | F78: 96.85 | G78: 54.66 | H78: 119.77 | I78: 151.42 | J78: 126.9 | K78: =J78 -> 126.9 | L78: =K78 -> 126.9 | M78: =L78 -> 126.9 | N78: =M78 -> 126.9 | O78: =N78 -> 126.9 | P78: =O78 -> 126.9
A79: Income Tax Assets | B79: 227.54 | C79: 331.94 | D79: 379.26 | E79: 839.26 | F79: 310.13 | G79: 368.19 | H79: 340.92 | I79: 251.72 | J79: 312.49 | K79: =J79 -> 312.49 | L79: =K79 -> 312.49 | M79: =L79 -> 312.49 | N79: =M79 -> 312.49 | O79: =N79 -> 312.49 | P79: =O79 -> 312.49
A81: Current Assets | B81: =SUM(B83:B90) -> 6151.22 | C81: =SUM(C83:C90) -> 7453.18 | D81: =SUM(D83:D90) -> 8848.18 | E81: =SUM(E83:E90) -> 8115.64 | F81: =SUM(F83:F90) -> 8288.56 | G81: =SUM(G83:G90) -> 10952.79 | H81: =SUM(H83:H90) -> 10114.96 | I81: =SUM(I83:I90) -> 9036.79 | ... P81: =SUM(P83:P90) -> 67853.949
A83: Inventories | B83: 672.98 | C83: 656.31 | D83: 823.58 | E83: 1072.37 | F83: 1091.97 | G83: 1469.55 | H83: 1122.65 | I83: 1434.09 | J83: 1443.76 | K83: =K155 -> 2017.8632 | L83: =L155 -> 2459.3604 | M83: =M155 -> 2999.3309 | N83: =N155 -> 3660.03 | O83: =O155 -> 4468.7875 | P83: =P155 -> 5459.171
A84: Receivables | B84: 1282.8 | C84: 1561.87 | D84: 1520.18 | E84: 2821.57 | F84: 1603.14 | G84: 2426.76 | H84: 2304.27 | I84: 2798.21 | J84: 2703.44 | K84: =K156 -> 4035.7263 | L84: =L156 -> 4918.7208 | M84: =M156 -> 5998.6618 | N84: =N156 -> 7320.0601 | O84: =O156 -> 8937.5751 | P84: =P156 -> 10918.342
A85: Cash & Bank Balances | B85: =26.95+104.41 -> 131.36 | C85: =15.4+121.33 -> 136.73 | D85: =34.38+106.96 -> 141.34 | E85: =40.68+95.78 -> 136.46 | F85: =147.91+93.95 -> 241.86 | G85: =169.22+87.93 -> 257.15 | H85: =98.68+76.44 -> 175.12 | I85: =168.37+177.13 -> 345.5 | J85: =539.89+69.04 -> 608.93 | K85: =K218 -> 2780.7084 | L85: =L218 -> 6439.2036 | M85: =M218 -> 10976.49 | N85: =N218 -> 16620.821 | O85: =O218 -> 23631.049 | P85: =P218 -> 32456.987
A86: Loans & Advances | B86: 23.12 | C86: 24.18 | D86: 27.56 | E86: 25.03 | F86: 22.36 | G86: 22.95 | H86: 22.81 | I86: 23.71 | J86: 24.56 | K86: =K157 -> 33.078205 | L86: =L157 -> 40.315532 | M86: =M157 -> 49.167101 | N86: =N157 -> 59.997737 | O86: =O157 -> 73.255448 | P86: =P157 -> 89.490497
A87: Other Current Assets | B87: 549.57 | C87: 388.29 | D87: 205.03 | E87: 239.22 | F87: 280.14 | G87: 213.37 | H87: 197.65 | I87: 235.07 | J87: 457.3 | K87: =K158 -> 429.43491 | L87: =L158 -> 508.60915 | M87: =M158 -> 640.44489 | N87: =N158 -> 814.15007 | O87: =O158 -> 1037.4934 | P87: =P158 -> 1187.6528
A88: Current Tax Asset | B88: 0 | C88: 0 | D88: 0 | E88: 0 | F88: 0 | G88: 0 | H88: 0 | I88: 0 | J88: 0 | K88: =K159 -> 0 | L88: =L159 -> 0 | M88: =M159 -> 0 | N88: =N159 -> 0 | O88: =O159 -> 0 | P88: =P159 -> 0
A89: Investments | B89: 3469.11 | C89: 4540.85 | D89: 5591.12 | E89: 3167.1 | F89: 4694.48 | G89: 6191.49 | H89: 5837.66 | I89: 3637.88 | J89: 4274.52 | K89: =K160 -> 6558.0553 | L89: =L160 -> 7992.9213 | M89: =M160 -> 9747.8254 | N89: =N160 -> 11895.098 | O89: =O160 -> 14523.56 | P89: =P160 -> 17742.306
A90: Other Financial Assets | B90: 22.28 | C90: 144.95 | D90: 539.37 | E90: 653.89 | F90: 354.61 | G90: 371.52 | H90: 454.8 | I90: 562.33 | J90: 283.51
A91: Total | B91: =SUM(B81,B68) -> 12572.86 | C91: =SUM(C81,C68) -> 14694.26 | D91: =SUM(D81,D68) -> 16738.8 | E91: =SUM(E81,E68) -> 17641.19 | F91: =SUM(F81,F68) -> 18749.33 | G91: =SUM(G81,G68) -> 22161.05 | H91: =SUM(H81,H68) -> 21714.02 | I91: =SUM(I68,I81) -> 23263.14 | J91: =SUM(J81,J68) -> 25571.55 | K91: =SUM(K81,K68) -> 32108.706 | L91: =SUM(L81,L68) -> 39111.371 | M91: =SUM(M81,M68) -> 47662.56 | N91: =SUM(N81,N68) -> 58119.197 | O91: =SUM(O81,O68) -> 70919.16 | P91: =SUM(P81,P68) -> 86599.789
A92: check (asset = liabilities) (should be zero) | B92: =B63-B91 -> 0 | C92: =C63-C91 -> -0.29 | D92: =D63-D91 -> 0.12 | E92: =E63-E91 -> -0.12 | F92: =F63-F91 -> -0.4 | G92: =G63-G91 -> -0.04 | H92: =H63-H91 -> 0.08 | I92: =I63-I91 -> -0.09 | ... P92: =P63-P91 -> 0.02
A94: Capacity | B94: 8100000 | C94: 9100000 | D94: 9100000 | E94: 9000000 | F94: 9100000 | G94: 9500000 | H94: 9500000 | I94: 9500000 | J94: 9500000 | K94: =J94+K95 -> 10300000 | L94: =K94+L95 -> 11100000 | M94: =L94+M95 -> 11900000 | N94: =M94+N95 -> 12700000 | O94: =N94+O95 -> 13500000 | P94: =O94+P95 -> 14300000
A95: New Capacity | C95: =C94-B94 -> 1000000 | D95: =D94-C94 -> 0 | E95: =E94-D94 -> -100000 | F95: =F94-E94 -> 100000 | G95: =G94-F94 -> 400000 | H95: =H94-G94 -> 0 | I95: =I94-H94 -> 0 | J95: =J94-I94 -> 0 | K95: 800000 | L95: 800000 | M95: 800000 | N95: 800000 | O95: 800000 | P95: 800000
A97: Domestic | B97: 6420000 | C97: 6482000 | D97: 7360000 | E97: 7610000 | F97: 6220000 | G97: 5600000 | H97: 4640000 | I97: 5156000 | J97: 5420000
A98: Exports | B98: 210409 | C98: 182117 | D98: 204476 | E98: 208056 | F98: 178261 | G98: 191609 | H98: 300624 | I98: 172753 | J98: 200923
A99: Total | B99: =SUM(B97:B98) -> 6630409 | C99: =SUM(C97:C98) -> 6664117 | D99: =SUM(D97:D98) -> 7564476 | E99: =SUM(E97:E98) -> 7818056 | F99: =SUM(F97:F98) -> 6398261 | G99: =SUM(G97:G98) -> 5791609 | H99: =SUM(H97:H98) -> 4940624 | I99: =SUM(I97:I98) -> 5328753 | J99: =SUM(J97:J98) -> 5620923 | K99: =K110*K117 -> 6945359.2 | L99: =L110*L117 -> 7766023.1 | M99: =M110*M117 -> 8689091.7 | N99: =N110*N117 -> 9727654.9 | O99: =O110*O117 -> 10896492 | P99: =P110*P117 -> 12212293
A101: Capacity Utilization | B101: =B99/B94 -> 0.81856901 | C101: =C99/C94 -> 0.73232055 | D101: =D99/D94 -> 0.8312611 | E101: =E99/E94 -> 0.86867289 | F101: =F99/F94 -> 0.7031056 | G101: =G99/G94 -> 0.60964305 | H101: =H99/H94 -> 0.52006568 | I101: =I99/I94 -> 0.56092137 | ... P101: =P99/P94 -> 0.85400648
A103: Growth in Domestic Sales | C103: =C97/B97-1 -> 0.0096573209 | D103: =D97/C97-1 -> 0.13545202 | E103: =E97/D97-1 -> 0.033967391 | F103: =F97/E97-1 -> -0.1826544 | G103: =G97/F97-1 -> -0.099678457 | H103: =H97/G97-1 -> -0.17142857 | I103: =I97/H97-1 -> 0.1112069 | J103: =J97/I97-1 -> 0.051202483
A104: Growth in Export Sales | C104: =C98/B98-1 -> -0.13446193 | D104: =D98/C98-1 -> 0.12277272 | E104: =E98/D98-1 -> 0.017508167 | F104: =F98/E98-1 -> -0.14320664 | G104: =G98/F98-1 -> 0.07487897 | H104: =H98/G98-1 -> 0.56894509 | I104: =I98/H98-1 -> -0.42535193 | J104: =J98/I98-1 -> 0.16306519
A105: Growth in Total Sales | C105: =C99/B99-1 -> 0.0050838493 | D105: =D99/C99-1 -> 0.13510552 | E105: =E99/D99-1 -> 0.033522481 | F105: =F99/E99-1 -> -0.18160461 | G105: =G99/F99-1 -> -0.094815138 | H105: =H99/G99-1 -> -0.14693412 | I105: =I99/H99-1 -> 0.0785587 | J105: =J99/I99-1 -> 0.054828963
A107: Industry Data
A108: Domestic Sales | B108: 16460000 | C108: 17590000 | D108: 20200000 | E108: 21179847 | F108: 17416432 | G108: 15120783 | H108: 13570008 | I108: 15862771 | J108: 17974365 | K108: =J108*(1+K111) -> 20311032 | L108: =K108*(1+L111) -> 22951467 | M108: =L108*(1+M111) -> 25935157 | N108: =M108*(1+N111) -> 29306728 | O108: =N108*(1+O111) -> 33116602 | P108: =O108*(1+P111) -> 37421761
A109: Exports | B109: 2500000 | C109: 2600000 | D109: 2800000 | E109: 3280841 | F109: 3519405 | G109: 3282786 | H109: 4443131 | I109: 3652122 | J109: 3458416 | K109: =J109*(1+K112) -> 3638482 | L109: =K109*(1+L112) -> 3827923.2 | M109: =L109*(1+M112) -> 4027228 | N109: =M109*(1+N112) -> 4236909.7 | O109: =N109*(1+O112) -> 4457508.7 | P109: =O109*(1+P112) -> 4689593.5
A110: Total | B110: =SUM(B108:B109) -> 18960000 | C110: =SUM(C108:C109) -> 20190000 | D110: =SUM(D108:D109) -> 23000000 | E110: =SUM(E108:E109) -> 24460688 | F110: =SUM(F108:F109) -> 20935837 | G110: =SUM(G108:G109) -> 18403569 | H110: =SUM(H108:H109) -> 18013139 | I110: =SUM(I108:I109) -> 19514893 | ... P110: =SUM(P108:P109) -> 42111354
A111: Growth in Domestic Market | C111: =C108/B108-1 -> 0.068651276 | D111: =D108/C108-1 -> 0.14837976 | E111: =E108/D108-1 -> 0.048507277 | F111: =F108/E108-1 -> -0.17768849 | G111: =G108/F108-1 -> -0.13180937 | H111: =H108/G108-1 -> -0.10255917 | I111: =I108/H108-1 -> 0.16895812 | J111: =J108/I108-1 -> 0.13311634 | K111: 0.13 | L111: =K111 -> 0.13 | M111: =L111 -> 0.13 | N111: =M111 -> 0.13 | O111: =N111 -> 0.13 | P111: =O111 -> 0.13
A112: Growth in Exports | C112: =C109/B109-1 -> 0.04 | D112: =D109/C109-1 -> 0.076923077 | E112: =E109/D109-1 -> 0.17172893 | F112: =F109/E109-1 -> 0.072714283 | G112: =G109/F109-1 -> -0.067232671 | H112: =H109/G109-1 -> 0.35346349 | I112: =I109/H109-1 -> -0.17802964 | J112: =J109/I109-1 -> -0.053039302 | K112: =AVERAGE(C112:J112) -> 0.052066021 | L112: =K112 -> 0.052066021 | M112: =L112 -> 0.052066021 | N112: =M112 -> 0.052066021 | O112: =N112 -> 0.052066021 | P112: =O112 -> 0.052066021
A114: Market Share
A115: Domestic | B115: =B97/B108 -> 0.39003645 | C115: =C97/C108 -> 0.36850483 | D115: =D97/D108 -> 0.36435644 | E115: =E97/E108 -> 0.35930382 | F115: =F97/F108 -> 0.357134 | G115: =G97/G108 -> 0.37035119 | H115: =H97/H108 -> 0.34193053 | I115: =I97/I108 -> 0.32503779 | J115: =J97/J108 -> 0.30154056
A116: Exports | B116: =B98/B109 -> 0.0841636 | C116: =C98/C109 -> 0.070045 | D116: =D98/D109 -> 0.073027143 | E116: =E98/E109 -> 0.063415447 | F116: =F98/F109 -> 0.050650891 | G116: =G98/G109 -> 0.058367801 | H116: =H98/H109 -> 0.067660395 | I116: =I98/I109 -> 0.047302089 | J116: =J98/J109 -> 0.058096828
A117: Overall | B117: =B99/B110 -> 0.34970512 | C117: =C99/C110 -> 0.33007018 | D117: =D99/D110 -> 0.32889026 | E117: =E99/E110 -> 0.31961718 | F117: =F99/F110 -> 0.30561286 | G117: =G99/G110 -> 0.31470032 | H117: =H99/H110 -> 0.2742789 | I117: =I99/I110 -> 0.27306084 | J117: =J99/J110 -> 0.26225822 | K117: 0.29 | L117: =K117 -> 0.29 | M117: =L117 -> 0.29 | N117: =M117 -> 0.29 | O117: =N117 -> 0.29 | P117: =O117 -> 0.29
A120: Revenue Per Vehicle(two wheeler) | B120: =(B3/B99)*10^7 -> 46303.147 | C120: =(C3/C99)*10^7 -> 46325.102 | D120: =(D3/D99)*10^7 -> 43455.515 | E120: =(E3/E99)*10^7 -> 43042.081 | F120: =(F3/F99)*10^7 -> 45068.637 | G120: =(G3/G99)*10^7 -> 53181.456 | H120: =(H3/H99)*10^7 -> 59193.879 | I120: =(I3/I99)*10^7 -> 63440.077 | J120: =(J3/J99)*10^7 -> 66636.245 | K120: =J120*(1+K121) -> 72633.507 | L120: =K120*(1+L121) -> 79170.522 | M120: =L120*(1+M121) -> 86295.869 | N120: =M120*(1+N121) -> 94062.497 | O120: =N120*(1+O121) -> 102528.12 | P120: =O120*(1+P121) -> 111755.65
A121: Growth | C121: =C120/B120-1 -> 0.00047416706 | D121: =D120/C120-1 -> -0.061944539 | E121: =E120/D120-1 -> -0.0095139573 | F121: =F120/E120-1 -> 0.047083122 | G121: =G120/F120-1 -> 0.18001032 | H121: =H120/G120-1 -> 0.11305488 | I121: =I120/H120-1 -> 0.07173373 | J121: =J120/I120-1 -> 0.050380893 | K121: 0.09 | L121: =K121 -> 0.09 | M121: =L121 -> 0.09 | N121: =M121 -> 0.09 | O121: =N121 -> 0.09 | P121: =O121 -> 0.09
A124: Cost Drivers
A125: Raw Materials | B125: =B9/B$3 -> 0.62935395 | C125: =C9/C$3 -> 0.61461395 | D125: =D9/D$3 -> 0.66494006 | E125: =E9/E$3 -> 0.69378084 | F125: =F9/F$3 -> 0.68896962 | G125: =G9/G$3 -> 0.71022369 | H125: =H9/H$3 -> 0.70807787 | I125: =I9/I$3 -> 0.71052413 | J125: =J9/J$3 -> 0.6612464 | K125: 0.685 | L125: =K125 -> 0.685 | M125: =L125 -> 0.685 | N125: =M125 -> 0.685 | O125: =N125 -> 0.685 | P125: =O125 -> 0.685
A126: Purchases | B126: =B10/B$3 -> 0 | C126: =C10/C$3 -> 0 | D126: =D10/D$3 -> 0 | E126: =E10/E$3 -> 0 | F126: =F10/F$3 -> 0 | G126: =G10/G$3 -> 0.00098894113 | H126: =H10/H$3 -> 0.0015711835 | I126: =I10/I$3 -> 0.0014030199 | J126: =J10/J$3 -> 0.012927265 | K126: =J126 -> 0.012927265 | L126: =K126 -> 0.012927265 | M126: =L126 -> 0.012927265 | N126: =M126 -> 0.012927265 | O126: =N126 -> 0.012927265 | P126: =O126 -> 0.012927265
A127: Changes in Stock in Trade | B127: =B11/B$3 -> -0.00038695959 | C127: =C11/C$3 -> 0.0020462179 | D127: =D11/D$3 -> -0.00070425063 | E127: =E11/E$3 -> -0.00084337428 | F127: =F11/F$3 -> -0.0058877608 | G127: =G11/G$3 -> -0.0046576984 | H127: =H11/H$3 -> 0.002486197 | I127: =I11/I$3 -> -0.0061835817 | J127: =J11/J$3 -> 0.0047819131 | K127: =J127 -> 0.0047819131 | L127: =K127 -> 0.0047819131 | M127: =L127 -> 0.0047819131 | N127: =M127 -> 0.0047819131 | O127: =N127 -> 0.0047819131 | P127: =O127 -> 0.0047819131
A128: Employee Cost | B128: =B12/B$3 -> 0.042862941 | C128: =C12/C$3 -> 0.045219893 | D128: =D12/D$3 -> 0.046852593 | E128: =E12/E$3 -> 0.051417897 | F128: =F12/F$3 -> 0.063867882 | G128: =G12/G$3 -> 0.061645512 | H128: =H12/H$3 -> 0.066179138 | I128: =I12/I$3 -> 0.064777042 | J128: =J12/J$3 -> 0.064138134 | K128: 0.065 | L128: 0.065 | M128: 0.065 | N128: 0.065 | O128: 0.065 | P128: 0.065
A129: Other Expenses | B129: =B13/B$3 -> 0.10950696 | C129: =C13/C$3 -> 0.11118183 | D129: =D13/D$3 -> 0.10877189 | E129: =E13/E$3 -> 0.10913614 | F129: =F13/F$3 -> 0.11579309 | G129: =G13/G$3 -> 0.10130738 | H129: =H13/H$3 -> 0.10649615 | I129: =I13/I$3 -> 0.1115633 | J129: =J13/J$3 -> 0.11658833 | K129: 0.11 | L129: 0.11 | M129: 0.11 | N129: 0.11 | O129: 0.11 | P129: 0.11
A133: Cost Per Car
A134: Raw Materials
A135: Purchases
A136: Changes in Stock in Trade
A137: Employee Cost
A138: Other Expenses
A139: Own Use Vehicles
A142: Growth
...

Sheet Excutesummary
A2: Terminal Value | B2: =Model!B223 -> 0.02 | D2: TG | K2: Cash Flow | L2: PV of FCFF | M2: Year
A3: Cash Growth | B3: =Model!B224 -> 0.035 | D3: =L21 -> 105441.5 | E3: 0.015 | F3: =E3+0.005 -> 0.02 | G3: =F3+0.005 -> 0.025 | H3: =G3+0.005 -> 0.03 | I3: =H3+0.005 -> 0.035 | J3: 0 | K3: {=INDEX(Model!$K$217:$V$217,,COLUMN(Model!A215)+Excutesummary!J3)} -> 2171.7784 | L3: =-PV($B$4,M3,,K3) -> 1939.0879 | M3: 1
A4: Discount Rate | B4: =Model!B225 -> 0.12 | C4: WACC | D4: =D5-0.005 -> 0.105 | E4: 125552.73 | F4: 129663.37 | G4: 134287.83 | H4: 139528.88 | I4: 145518.66 | J4: 1 | K4: {=INDEX(Model!$K$217:$V$217,,COLUMN(Model!A216)+Excutesummary!J4)} -> 3658.4952 | L4: =-PV($B$4,M4,,K4) -> 2916.53 | M4: 2
A5: Risk free rate | B5: =Model!B226 -> 0.07 | D5: =D6-0.005 -> 0.11 | E5: 117121.44 | F5: 120621.18 | G5: 124532.66 | H5: 128933.07 | I5: 133920.21 | J5: 2 | K5: {=INDEX(Model!$K$217:$V$217,,COLUMN(Model!A217)+Excutesummary!J5)} -> 4537.2867 | L5: =-PV($B$4,M5,,K5) -> 3229.5511 | M5: 3
A6: Market Premium | B6: =Model!B227 -> 0.05 | D6: =D7-0.005 -> 0.115 | E6: 109601.3 | F6: 112599.13 | G6: 115930.06 | H6: 119652.87 | I6: 123841.02 | J6: 3 | K6: {=INDEX(Model!$K$217:$V$217,,COLUMN(Model!A218)+Excutesummary!J6)} -> 5644.3309 | L6: =-PV($B$4,M6,,K6) -> 3587.0743 | M6: 4
A7: Switch MP | B7: =Model!B228 -> 1 | D7: 0.12 | E7: 102859.43 | F7: 105441.5 | G7: 108295.37 | H7: 111466.33 | I7: 115010.34 | J7: 4 | K7: {=INDEX(Model!$K$217:$V$217,,COLUMN(Model!A219)+Excutesummary!J7)} -> 7010.2274 | L7: =-PV($B$4,M7,,K7) -> 3977.7913 | M7: 5
A8: PV of FCFF | B8: =Model!B229 -> 100274.54 | D8: =D7+0.005 -> 0.125 | E8: 96787.258 | F8: 99022.35 | G8: 101480.95 | H8: 104198.35 | I8: 107217.69 | J8: 5 | K8: {=INDEX(Model!$K$217:$V$217,,COLUMN(Model!A220)+Excutesummary!J8)} -> 8825.9383 | L8: =-PV($B$4,M8,,K8) -> 4471.495 | M8: 6
A9: Cash as on today (T) | B9: =Model!B230 -> 5166.96 | D9: =D8+0.005 -> 0.13 | E9: 91295.176 | F9: 93238.753 | G9: 95367.433 | H9: 97708.98 | I9: 100297.01 | J9: 6 | K9: {=INDEX(Model!$K$217:$V$217,,COLUMN(Model!A221)+Excutesummary!J9)} -> 10803.026 | L9: =-PV($B$4,M9,,K9) -> 4886.7405 | M9: 7
A10: Enterprise Value | B10: =Model!B231 -> 105441.5 | J10: 7 | K10: {=INDEX(Model!$K$217:$V$217,,COLUMN(Model!A222)+Excutesummary!J10)} -> 12844.894 | L10: =-PV($B$4,M10,,K10) -> 5187.8372 | M10: 8
A11: No of Shares | B11: =Model!B232 -> 20 | J11: 8 | K11: {=INDEX(Model!$K$217:$V$217,,COLUMN(Model!A223)+Excutesummary!J11)} -> 14823.121 | L11: =-PV($B$4,M11,,K11) -> 5345.3661 | M11: 9
A12: Per Share value | B12: =Model!B233 -> 5272.0751 | J12: 9 | K12: {=INDEX(Model!$K$217:$V$217,,COLUMN(Model!A224)+Excutesummary!J12)} -> 16587.203 | L12: =-PV($B$4,M12,,K12) -> 5340.6356 | M12: 10
A13: Current share price | B13: =Model!B234 -> 5418 | J13: 10 | K13: {=INDEX(Model!$K$217:$V$217,,COLUMN(Model!A225)+Excutesummary!J13)} -> 17980.675 | L13: =-PV($B$4,M13,,K13) -> 5169.0144 | M13: 11
B14: =B13-B12 -> 145.92493 | C14: P/L | J14: 11 | K14: {=INDEX(Model!$K$217:$V$217,,COLUMN(Model!A226)+Excutesummary!J14)} -> 18861.887 | L14: =-PV($B$4,M14,,K14) -> 4841.3766 | M14: 12
A15: Valuation Status | B15: =IF(B13>B12,"OverValued","UnderValued") -> OverValued | C15: =B12/B13-1 -> -0.026933356 | G15: Metric | H15: CAGR | K15: total | L15: =SUM(L3:L14) -> 50892.5
G16: Revenue | H16: =POWER(Model!P3/Model!K3,1/6)-1 -> 0.18042708
G17: PAT | H17: =POWER(Model!P209/Model!K209,1/6)-1 -> 0.18180171 | K17: TV | L17: =K14*(1+B2)/(B4-B2) -> 192391.25
B18: Year | C18: Revenue | D18: EBIDTA | E18: Margin | G18: Cash Flow | H18: =POWER(Model!P217/Model!K217,1/6)-1 -> 0.26325462 | K18: PV of TV | L18: =-PV(B4,M14,,L17) -> 49382.041
A19: 0 | B19: 2020A | C19: {=INDEX(Model!$F$3:$P$3,,COLUMN(Model!$A$1)+A19)} -> 28836.09 | D19: {=INDEX(Model!$F$18:$P$18,,COLUMN(Model!$A$1)+Excutesummary!A19)} -> 4736.3 | E19: =D19/C19 -> 0.16424904 | L19: =L15+L18 -> 100274.54
A20: 1 | B20: 2021A | C20: {=INDEX(Model!$F$3:$P$3,,COLUMN(Model!$A$1)+A20)} -> 30800.62 | D20: {=INDEX(Model!$F$18:$P$18,,COLUMN(Model!$A$1)+Excutesummary!A20)} -> 4599.09 | E20: =D20/C20 -> 0.1493181 | K20: Cash | L20: =B9 -> 5166.96
A21: 2 | B21: 2022A | C21: {=INDEX(Model!$F$3:$P$3,,COLUMN(Model!$A$1)+A21)} -> 29245.47 | D21: {=INDEX(Model!$F$18:$P$18,,COLUMN(Model!$A$1)+Excutesummary!A21)} -> 3925.68 | E21: =D21/C21 -> 0.13423207 | K21: Ev | L21: =L19+L20 -> 105441.5
A22: 3 | B22: 2023A | C22: {=INDEX(Model!$F$3:$P$3,,COLUMN(Model!$A$1)+A22)} -> 33805.65 | D22: {=INDEX(Model!$F$18:$P$18,,COLUMN(Model!$A$1)+Excutesummary!A22)} -> 4551.39 | E22: =D22/C22 -> 0.134634
A23: 4 | B23: 2024A | C23: {=INDEX(Model!$F$3:$P$3,,COLUMN(Model!$A$1)+A23)} -> 37455.72 | D23: {=INDEX(Model!$F$18:$P$18,,COLUMN(Model!$A$1)+Excutesummary!A23)} -> 6148.26 | E23: =D23/C23 -> 0.16414743
A24: 5 | B24: 2025E | C24: {=INDEX(Model!$F$3:$P$3,,COLUMN(Model!$A$1)+A24)} -> 50446.579 | D24: {=INDEX(Model!$F$18:$P$18,,COLUMN(Model!$A$1)+Excutesummary!A24)} -> 6734.3137 | E24: =D24/C24 -> 0.13349396 | G24: TG | H24: =E3 -> 0.015 | I24: =F3 -> 0.02 | J24: =G3 -> 0.025 | K24: =H3 -> 0.03 | L24: =I3 -> 0.035
A25: 6 | B25: 2026E | C25: {=INDEX(Model!$F$3:$P$3,,COLUMN(Model!$A$1)+A25)} -> 61484.01 | D25: {=INDEX(Model!$F$18:$P$18,,COLUMN(Model!$A$1)+Excutesummary!A25)} -> 8084.0902 | E25: =D25/C25 -> 0.13148281 | G25: WACC
A26: 7 | B26: 2027E | C26: {=INDEX(Model!$F$3:$P$3,,COLUMN(Model!$A$1)+A26)} -> 74983.272 | D26: {=INDEX(Model!$F$18:$P$18,,COLUMN(Model!$A$1)+Excutesummary!A26)} -> 9734.926 | E26: =D26/C26 -> 0.12982797 | G26: =D4 -> 0.105 | H26: =E4 -> 125552.73 | I26: =F4 -> 129663.37 | J26: =G4 -> 134287.83 | K26: =H4 -> 139528.88 | L26: =I4 -> 145518.66
A27: 8 | B27: 2028E | C27: {=INDEX(Model!$F$3:$P$3,,COLUMN(Model!$A$1)+A27)} -> 91500.751 | D27: {=INDEX(Model!$F$18:$P$18,,COLUMN(Model!$A$1)+Excutesummary!A27)} -> 11754.862 | E27: =D27/C27 -> 0.12846738 | G27: =D5 -> 0.11 | H27: =E5 -> 117121.44 | I27: =F5 -> 120621.18 | J27: =G5 -> 124532.66 | K27: =H5 -> 128933.07 | L27: =I5 -> 133920.21
A28: 9 | B28: 2029E | C28: {=INDEX(Model!$F$3:$P$3,,COLUMN(Model!$A$1)+A28)} -> 111719.69 | D28: {=INDEX(Model!$F$18:$P$18,,COLUMN(Model!$A$1)+Excutesummary!A28)} -> 14227.453 | E28: =D28/C28 -> 0.12734955 | G28: =D6 -> 0.115 | H28: =E6 -> 109601.3 | I28: =F6 -> 112599.13 | J28: =G6 -> 115930.06 | K28: =H6 -> 119652.87 | L28: =I6 -> 123841.02
A29: 10 | B29: 2030E | C29: {=INDEX(Model!$F$3:$P$3,,COLUMN(Model!$A$1)+A29)} -> 136479.28 | D29: {=INDEX(Model!$F$18:$P$18,,COLUMN(Model!$A$1)+Excutesummary!A29)} -> 17255.323 | E29: =D29/C29 -> 0.12643182 | G29: =D7 -> 0.12 | H29: =E7 -> 102859.43 | I29: =F7 -> 105441.5 | J29: =G7 -> 108295.37 | K29: =H7 -> 111466.33 | L29: =I7 -> 115010.34
G30: =D8 -> 0.125 | H30: =E8 -> 96787.258 | I30: =F8 -> 99022.35 | J30: =G8 -> 101480.95 | K30: =H8 -> 104198.35 | L30: =I8 -> 107217.69
G31: =D9 -> 0.13 | H31: =E9 -> 91295.176 | I31: =F9 -> 93238.753 | J31: =G9 -> 95367.433 | K31: =H9 -> 97708.98 | L31: =I9 -> 100297.01
B32: Metrics | C32: Historical Average | D32: Projection
B33: Raw Materials | C33: =AVERAGE(Model!B125:J125) -> 0.67574783 | D33: =Model!K125 -> 0.685
B34: Purchases | C34: =AVERAGE(Model!B126:J126) -> 0.0018767121 | D34: =Model!K126 -> 0.012927265
B35: Changes in Stock in Trade | C35: =AVERAGE(Model!H127:J127) -> 0.00036150947 | D35: =Model!K127 -> 0.0047819131 | G35: Item | H35: FY 2025E | J35: Year | K35: COGS | L35: Inventory | M35: Payables
B36: Employee Cost | C36: =AVERAGE(Model!B128:J128) -> 0.056329004 | D36: =Model!K128 -> 0.065 | G36: PAT (Net Profit) | H36: =Model!K209 -> 4145.8996 | J36: 2020 | K36: =Model!F9+Model!F10+Model!F11 -> 19697.41 | L36: =Model!F83 -> 1091.97 | M36: =Model!F59 -> 3030.51
B37: Other Expenses | C37: =AVERAGE(Model!B129:J129) -> 0.11003834 | D37: =Model!K129 -> 0.11 | G37: Add : Depreciation | H37: =Model!K210 -> 793.1 | J37: 2021 | K37: =Model!G9+Model!G10+Model!G11 -> 21762.33 | L37: =Model!G83 -> 1469.55 | M37: =Model!G59 -> 5205
G38: Add : Change in Debt | H38: =Model!K211 -> 0 | J38: 2022 | K38: =Model!H9+Model!H10+Model!H11 -> 20826.73 | L38: =Model!H83 -> 1122.65 | M38: =Model!H59 -> 4260.34
G39: Less : Change in working Capital | H39: =Model!K212 -> 1495.8111 | J39: 2023 | K39: =Model!I9+Model!I10+Model!I11 -> 23858.12 | L39: =Model!I83 -> 1434.09 | M39: =Model!I59 -> 4704.46
G40: Less : CAPEX | H40: =Model!K213 -> 1271.41 | J40: 2024 | K40: =Model!J9+Model!J10+Model!J11 -> 25430.77 | L40: =Model!J83 -> 1443.76 | M40: =Model!J59 -> 5528.15
B41: opening debt | C41: =Model!I51+Model!I52+Model!I58 -> 352.6 | G41: FCFF | H41: =H36+H37+H38-H39-H40 -> 2171.7784
B42: closing debt | C42: =Model!J51+Model!J52+Model!J58 -> 315.71
B43: Average debt | C43: =(C41+C42)/2 -> 334.155
B44: Interest | C44: =Model!J24 -> 18.5

Sheet Dashboard
W8: REVENUE & GROWTH | AB8: PROFITABILITY
W9: Base year Revenue(FY2024) | Z9: =Model!K3 -> 50446.579 | AC9: EBITDA margin FY(24) | AF9: =Model!J18/Model!J3 -> 0.16414743
W10: Revenue CAGR | Z10: =POWER(Model!J3/Model!F3,1/5)-1 -> 0.053698485 | AC10: EBITDA margin FY(30) | AF10: =Model!P18/Model!P3 -> 0.12643182
W11: Terminal Growth Rate | Z11: =Model!B223 -> 0.02 | AC11: Tax Rate | AF11: =AVERAGE(Model!F32:J32) -> 0.23541105
W14: CAPITAL EXPENDITURE | AB14: WORKING CAPITAL
W15: Capex as % of Revenue | Z15: =AVERAGE(Model!F196/Model!F3,Model!G196/Model!G3,Model!H196/Model!H3,Model!I196/Model!I3,Model!J196/Model!J3) -> 0.19990228 | AC15: WC as % of Revenue | AF15: =AVERAGE(Model!F189/Model!F170,Model!G189/Model!G170,Model!H189/Model!H170,Model!I189/Model!I170,Model!J189/Model!J170) -> 0.1235507
W16: Depreciation % of Revenue | Z16: =AVERAGE(Model!F20/Model!F3,Model!G20/Model!G3,Model!H20/Model!H3,Model!I20/Model!I3,Model!J20/Model!J3) -> 0.022197123 | AC16: Days Payable Outstanding | AF16: =AVERAGE(Excutesummary!M36/Excutesummary!K36*365,Excutesummary!M37/Excutesummary!K37*365,Excutesummary!M38/Excutesummary!K38*365,Excutesummary!M39/Excutesummary!K39*365,Excutesummary!M40/Excutesummary!K40*365) -> 73.887268
AC17: Days Sales Outstanding | AF17: =AVERAGE(Model!F156/Model!F170*365,Model!G156/Model!G170*365,Model!H156/Model!H170*365,Model!I156/Model!I170*365,Model!J156/Model!J170*365) -> 26.873147
AC18: Days Inventory | AF18: =AVERAGE(Excutesummary!L36/Excutesummary!K36*365,Excutesummary!L37/Excutesummary!K37*365,Excutesummary!L38/Excutesummary!K38*365,Excutesummary!L39/Excutesummary!K39*365,Excutesummary!L40/Excutesummary!K40*365) -> 21.443752
W20: WEIGHTED AVERAGE COST OF CAPITAL (WACC)
W21: Rirsk Free Rate | Z21: =Model!B226 -> 0.07 | AC21: Cost of Equity | AF21: =Z21+Z22*Z23 -> 0.12
W22: Beta | Z22: =Model!B228 -> 1 | AC22: Cost of Debt | AF22: =(Excutesummary!C44/Excutesummary!C43)*(1-Dashboard!Z24) -> 0.03875447
W23: Market-Risk Premium | Z23: =Model!B227 -> 0.05 | AC23: Equity Weight | AF23: =(Model!B234*Model!B232)/Model!B231 -> 1.0276788
W24: Tax Rate | Z24: =Model!K32 -> 0.3 | AC24: Debt Weight | AF24: 0

Sheet Notes & Assumptions
A1: Notes & Assumptions – Hero MotoCorp Ltd. Valuation Model
A2: This valuation model estimates the intrinsic value of Hero MotoCorp Ltd. using a Discounted Cash Flow (DCF) approach on a standalone basis (values in ₹ crore). Forecast period covers FY2025–FY2030, followed by a terminal value
A4: Revenue & Market Assumptions
A5: Historical other income has been volatile, ranging from ₹422 crore to ₹893 crore over the last nine years.
A6: To avoid overstating or understating the long-term cash flows, using the median historical value of ₹565 crore as a stable estimate
A7: Domestic two-wheeler industry growth assumed at 13% per annum.
A8: Export market growth assumed at 5.21%, in line with historical average
A9: Market share is assumed to stabilise around 29%, reflecting Hero MotoCorp’s strong brand equity and competitive positioning despite market fragmentation.
A11: Volume Forecast
A13: Volumes are based on:
A14: Installed production capacity of existing plants (Haridwar, Gurugram, Neemrana, Halol).
A15: Expected commissioning of the Chittoor plant by FY2025
... A85: Impact: Stock is trading at a small premium (~2.7%), meaning it is slightly overvalued.
